omegacloud_cli/__init__.py
omegacloud_cli/api.py
omegacloud_cli/main.py
omegacloud_cli/common/__init__.py
omegacloud_cli/common/enums.py
omegacloud_cli/common/schemas.py
omegacloud_cli/controllers/filesync.py
omegacloud_cli/utils/__init__.py
omegacloud_cli/utils/config.py
omegacloud_cli/utils/packing.py
omegacloud_cli/utils/py_packaging.py
omegacloud_cli/utils/schedule.py
omegacloud_cli-0.1.20.dist-info/METADATA
omegacloud_cli-0.1.20.dist-info/WHEEL
omegacloud_cli-0.1.20.dist-info/entry_points.txt
omegacloud_cli-0.1.20.dist-info/licenses/LICENSE
omegacloud_cli-0.1.20.dist-info/RECORD
