Metadata-Version: 2.4
Name: omegacloud-cli
Version: 0.1.20
Summary: CLI for OmegaCloud.ai
Project-URL: Homepage, https://omegacloud.ai
Project-URL: Documentation, https://omegacloud.ai/
Author-email: OmegaCloud <hello@omegacloud.ai>
License: Custom
License-File: LICENSE
Requires-Python: >=3.8
Requires-Dist: aiofiles>=24.1.0
Requires-Dist: asyncclick>=8.1.7.2
Requires-Dist: click>=8.1.7
Requires-Dist: cron-descriptor>=1.4.5
Requires-Dist: croniter>=6.0.0
Requires-Dist: httpx>=0.28.1
Requires-Dist: inquirerpy>=0.3.4
Requires-Dist: packaging>=23.2
Requires-Dist: pydantic>=2.10.6
Requires-Dist: pyyaml>=6.0.1
Requires-Dist: requests>=2.31.0
Requires-Dist: rich>=13.9.4
Requires-Dist: toml>=0.10.2
